{"cameraMode":{"drawMode":0,"name":"Shaded","section":"Shading Mode"},"sceneLighting":true,"audioPlay":false,"sceneViewState":{"showFog":true,"showMaterialUpdate":false,"showSkybox":true,"showFlares":true,"showImageEffects":true,"showParticleSystems":true},"in2DMode":false,"pivot":{"x":1.8086025714874268,"y":-1.6800694465637208,"z":6.761537075042725},"rotation":{"x":0.22962786257266999,"y":-0.04086655005812645,"z":0.009645262733101845,"w":0.9723908305168152},"size":26.960744857788087,"orthographic":false}